aces/__init__.py
aces/idt/__init__.py
aces/idt/application.py
aces/idt/core/__init__.py
aces/idt/core/common.py
aces/idt/core/constants.py
aces/idt/core/structures.py
aces/idt/core/transform_id.py
aces/idt/framework/__init__.py
aces/idt/framework/project_settings.py
aces/idt/generators/__init__.py
aces/idt/generators/base_generator.py
aces/idt/generators/log_camera.py
aces/idt/generators/prelinearized_idt.py
aces/idt/generators/tonemapped_idt.py
idt_calculator-0.1.0.dist-info/METADATA
idt_calculator-0.1.0.dist-info/WHEEL
idt_calculator-0.1.0.dist-info/licenses/LICENSE.md
idt_calculator-0.1.0.dist-info/RECORD
