Metadata-Version: 2.4
Name: idt-calculator
Version: 0.1.0
Summary: An ACES Input Device Transform (IDT) calculator
Project-URL: Homepage, https://www.oscars.org/science-technology/sci-tech-projects/aces
Project-URL: Repository, https://github.com/ampas/idt-calculator
Project-URL: Issues, https://github.com/ampas/idt-calculator/issues
Project-URL: Changelog, https://github.com/ampas/idt-calculator/releases
Author-email: Alex Forsythe <aforsythe@oscars.org>, Thomas Mansencal <thomas.mansencal@gmail.com>, Adam Davis <adamdavis@netflix.com>
Maintainer-email: Alex Forsythe <aforsythe@oscars.org>, Thomas Mansencal <thomas.mansencal@gmail.com>, Adam Davis <adamdavis@netflix.com>
License: License Terms for Academy Color Encoding System Components
License-File: LICENSE.md
Keywords: aces,ampas,color,color-science,color-space,color-spaces,colorspace,colorspaces,colour,colour-science,colour-space,colour-spaces,colourspace,colourspaces,dash,docker,python
Classifier: Development Status :: 3 - Alpha
Classifier: Environment :: Console
Classifier: Intended Audience :: Developers
Classifier: Intended Audience :: Science/Research
Classifier: License :: OSI Approved
Classifier: Natural Language :: English
Classifier: Operating System :: OS Independent
Classifier: Programming Language :: Python :: 3
Classifier: Topic :: Scientific/Engineering
Classifier: Topic :: Software Development
Requires-Python: <3.14,>=3.10
Requires-Dist: colour-checker-detection>=0.2.1
Requires-Dist: colour-datasets>=0.2.5
Requires-Dist: colour-science>=0.4.5
Requires-Dist: dash
Requires-Dist: dash-bootstrap-components
Requires-Dist: dash-renderer
Requires-Dist: dash-uploader
Requires-Dist: gunicorn
Requires-Dist: imageio<3,>=2
Requires-Dist: jsonpickle<3,>=2
Requires-Dist: matplotlib>=3.7
Requires-Dist: networkx<4,>=3
Requires-Dist: numpy<3,>=1.24
Requires-Dist: openimageio==3.0.4.0
Requires-Dist: packaging<=21.3
Requires-Dist: pandas<3,>=2
Requires-Dist: plotly
Requires-Dist: scipy<2,>=1.10
Requires-Dist: typing-extensions<5,>=4
Requires-Dist: xxhash<4,>=3
